[
        {
                "id": "com.tbd.products.vip.30Days",
                "price": 4,
                "sum": 4,
                "tittle": "1 Month"
        },
        {
                "id": "com.tbd.products.vip.60Days",
                "price": 3.2,
                "sum": 9.6,
                "tittle": "3 Months"
        },
        {
                "id": "com.tbd.products.vip.120Days",
                "price": 2.56,
                "sum": 15.36,
                "tittle": "6 Month"
        },
        {
                "id": "com.tbd.products.vip.360Days",
                "price": 2.05,
                "sum": 24.6,
                "tittle": "1 Year"
        }
]